setup.cfg
setup.py
lava_dev_tool/__init__.py
lava_dev_tool/actions.py
lava_dev_tool/bzr_helper.py
lava_dev_tool/ci.py
lava_dev_tool/component.py
lava_dev_tool/document.py
lava_dev_tool/errors.py
lava_dev_tool/extcmd.py
lava_dev_tool/interface.py
lava_dev_tool/localenv.py
lava_dev_tool/main.py
lava_dev_tool/methods.py
lava_dev_tool/pathnames.py
lava_dev_tool/project.py
lava_dev_tool/renderer.py
lava_dev_tool/state.py
lava_dev_tool/ui.py
lava_dev_tool/utils.py
lava_dev_tool.egg-info/PKG-INFO
lava_dev_tool.egg-info/SOURCES.txt
lava_dev_tool.egg-info/dependency_links.txt
lava_dev_tool.egg-info/entry_points.txt
lava_dev_tool.egg-info/requires.txt
lava_dev_tool.egg-info/top_level.txt
lava_dev_tool.egg-info/zip-safe
lava_dev_tool/commands/__init__.py
lava_dev_tool/commands/component.py
lava_dev_tool/commands/localenv.py
lava_dev_tool/commands/project.py
lava_dev_tool/tests/__init__.py
lava_dev_tool/tests/helpers.py
lava_dev_tool/tests/test_component.py
lava_dev_tool/tests/test_document.py
lava_dev_tool/tests/test_project.py