Metadata-Version: 1.0
Name: lava-dev-tool
Version: 0.1.dev33
Summary: LAVA development tool is a reproducible builder and release helper focused on complex python projects
Home-page: http://launchpad.net/lava-dev-tool/
Author: Linaro Validation Team
Author-email: linaro-dev@lists.linaro.org
License: LGPLv3
Platform: UNKNOWN
Classifier: Development Status :: 3 - Alpha
Classifier: Intended Audience :: Developers
Classifier: License :: OSI Approved :: GNU Library or Lesser General Public License (LGPL)
Classifier: Operating System :: OS Independent
Classifier: Programming Language :: Python :: 2.6
Classifier: Programming Language :: Python :: 2.7
Classifier: Topic :: Software Development :: Build Tools
Classifier: Topic :: Software Development :: Testing
